pypi2aur/__init__.py
pypi2aur/click.py
pypi2aur/constants.py
pypi2aur/kernel.py
pypi2aur/util.py
pypi2aur-0.1.14.dist-info/METADATA
pypi2aur-0.1.14.dist-info/WHEEL
pypi2aur-0.1.14.dist-info/entry_points.txt
pypi2aur-0.1.14.dist-info/licenses/LICENSE
pypi2aur-0.1.14.dist-info/RECORD
