Metadata-Version: 2.4
Name: pypi2aur
Version: 0.1.14
Summary: PyPi to AUR PKGBUILD generator and helper.
Project-URL: homepage, https://github.com/AntraXClown/pypi2aur
Project-URL: Repository, https://github.com/AntraXClown/pypi2aur
Author-email: Antrax <fredcox@gmail.com>
License: MIT
License-File: LICENSE
Requires-Python: >=3.13
Requires-Dist: click>=8.1.8
Requires-Dist: python-slugify>=8.0.4
Requires-Dist: requests>=2.32.3
Requires-Dist: rich>=14.0.0
